djpatterns/exception.py
djpatterns/repository.py
djpatterns/responsability.py
djpatterns-0.1.2.dist-info/DESCRIPTION.rst
djpatterns-0.1.2.dist-info/METADATA
djpatterns-0.1.2.dist-info/RECORD
djpatterns-0.1.2.dist-info/WHEEL
djpatterns-0.1.2.dist-info/metadata.json
djpatterns-0.1.2.dist-info/top_level.txt
dpatterns/exception.py
dpatterns/repository.py
