Metadata-Version: 2.0
Name: djpatterns
Version: 0.1.2
Summary: A helper for desgin patterns in python
Home-page: https://github.com/mandala21/desgin_patterns
Author: Lucas Resende
Author-email: lucasresone@gmail.com
License: MIT
Platform: UNKNOWN
